pandas_gsheets/__init__.py
pandas_gsheets/gsheets.py
pandas_gsheets/setup.py
pandas_gsheets-0.0.0.dist-info/METADATA
pandas_gsheets-0.0.0.dist-info/WHEEL
pandas_gsheets-0.0.0.dist-info/RECORD
